nonebot/adapters/vocechat/__init__.py
nonebot/adapters/vocechat/adapter.py
nonebot/adapters/vocechat/api.py
nonebot/adapters/vocechat/bot.py
nonebot/adapters/vocechat/bot.pyi
nonebot/adapters/vocechat/config.py
nonebot/adapters/vocechat/event.py
nonebot/adapters/vocechat/message.py
nonebot/adapters/vocechat/utils.py
nonebot_adapter_vocechat-0.1.6.dist-info/METADATA
nonebot_adapter_vocechat-0.1.6.dist-info/WHEEL
nonebot_adapter_vocechat-0.1.6.dist-info/entry_points.txt
nonebot_adapter_vocechat-0.1.6.dist-info/RECORD
