Metadata-Version: 2.1
Name: nonebot-adapter-vocechat
Version: 0.1.6
Summary: 一个 nonebot 的 Vocechat 适配器
Author-Email: 5656565566 <2393963330@qq.com>
License: MIT
Project-URL: homepage, https://github.com/5656565566/nonebot-adapter-vocechat
Project-URL: repository, https://github.com/5656565566/nonebot-adapter-vocechat
Requires-Python: >=3.10
Requires-Dist: nonebot2<3.0.0,>=2.4.2
